README.md
setup.py
pycoMeth/CGI_Finder.py
pycoMeth/Comp_Report.py
pycoMeth/CoordGen.py
pycoMeth/FileParser.py
pycoMeth/Meth_Comp.py
pycoMeth/Meth_Seg.py
pycoMeth/__init__.py
pycoMeth/__main__.py
pycoMeth/common.py
pycoMeth/loader.py
pycoMeth.egg-info/PKG-INFO
pycoMeth.egg-info/SOURCES.txt
pycoMeth.egg-info/dependency_links.txt
pycoMeth.egg-info/entry_points.txt
pycoMeth.egg-info/requires.txt
pycoMeth.egg-info/top_level.txt
pycoMeth/meth_seg/__init__.py
pycoMeth/meth_seg/emissions.py
pycoMeth/meth_seg/hmm.py
pycoMeth/meth_seg/math.py
pycoMeth/meth_seg/postprocessing.py
pycoMeth/meth_seg/segment.py
pycoMeth/meth_seg/segments_csv_io.py
pycoMeth/templates/CpG_Interval.html.j2
pycoMeth/templates/CpG_summary.html.j2