Metadata-Version: 2.1
Name: pycoMeth
Version: 2.2.2
Summary: Differential methylation calling suite for Nanopore methylation calls PycoMeth
Home-page: https://github.com/snajder-r/pycoMeth,
Author: Rene Snajder
Author-email: r.snajder@dkfz-heidelberg.de
License: GPL
Platform: UNKNOWN
Classifier: Development Status :: 4 - Beta
Classifier: Intended Audience :: Science/Research
Classifier: Topic :: Scientific/Engineering :: Bio-Informatics
Classifier: License :: OSI Approved :: MIT License
Classifier: Programming Language :: Python :: 3
Requires-Python: >=3.7
